youtubecrawling/__init__.py
youtubecrawling-1.0.4.dist-info/METADATA
youtubecrawling-1.0.4.dist-info/WHEEL
youtubecrawling-1.0.4.dist-info/top_level.txt
youtubecrawling-1.0.4.dist-info/RECORD
